nju_login.py
nju_login_simple-1.1.4.dist-info/licenses/LICENSE
nju_login_simple-1.1.4.dist-info/METADATA
nju_login_simple-1.1.4.dist-info/WHEEL
nju_login_simple-1.1.4.dist-info/top_level.txt
nju_login_simple-1.1.4.dist-info/RECORD
