Metadata-Version: 2.4
Name: nju-login-simple
Version: 1.1.4
Summary: Login to authserver.nju.edu.cn, using python requests
Requires-Python: >=3.8
License-File: LICENSE
Requires-Dist: ddddocr>=1.5.6
Requires-Dist: lxml>=6.0.0
Requires-Dist: onnxruntime==1.19.2
Requires-Dist: pycryptodomex>=3.23.0
Requires-Dist: requests>=2.32.4
Dynamic: license-file
